Metadata-Version: 2.1
Name: algos777
Version: 0.0
Summary: Gaussian and Binomial distributions
Author-email: ja.s.p.erx.chu.a@gmail.com
